mroudai_django_slots-0.1.0.dist-info/licenses/LICENSE
slots/__init__.py
slots/apps.py
slots/engine.py
slots/selectors.py
slots/utils.py
slots/tests/__init__.py
slots/tests/fakes.py
slots/tests/settings.py
slots/tests/test_engine.py
slots/tests/test_selectors.py
slots/tests/test_utils.py
mroudai_django_slots-0.1.0.dist-info/METADATA
mroudai_django_slots-0.1.0.dist-info/WHEEL
mroudai_django_slots-0.1.0.dist-info/top_level.txt
mroudai_django_slots-0.1.0.dist-info/RECORD
