Metadata-Version: 2.4
Name: mroudai-django-slots
Version: 0.1.0
Summary: Generate bookable slot candidates for appointment booking systems.
Author-email: Kevin Oudai <kevin@mroudai.com>
License: MIT
Project-URL: Homepage, https://github.com/Kevin-Oudai/django-slots
Project-URL: Repository, https://github.com/Kevin-Oudai/django-slots
Keywords: django,appointments,availability,booking,slots
Classifier: Framework :: Django
Classifier: Framework :: Django :: 4.2
Classifier: Framework :: Django :: 5.0
Classifier: License :: OSI Approved :: MIT License
Classifier: Programming Language :: Python
Classifier: Programming Language :: Python :: 3
Classifier: Programming Language :: Python :: 3 :: Only
Classifier: Programming Language :: Python :: 3.10
Classifier: Programming Language :: Python :: 3.11
Classifier: Programming Language :: Python :: 3.12
Classifier: Topic :: Office/Business :: Scheduling
Requires-Python: >=3.10
License-File: LICENSE
Requires-Dist: Django>=4.2
Provides-Extra: test
Requires-Dist: pytest; extra == "test"
Requires-Dist: pytest-django; extra == "test"
Dynamic: license-file
